{
  "id": "hero",
  "type": "SharedSlice",
  "name": "Hero",
  "description": "Hero",
  "variations": [
    {
      "id": "default",
      "name": "Default",
      "docURL": "...",
      "version": "sktwi1xtmkfgx8626",
      "description": "Hero",
      "primary": {
        "heroheadline": {
          "type": "Text",
          "config": {
            "label": "HeroHeadline",
            "placeholder": ""
          }
        },
        "heroheadlinespan": {
          "type": "Text",
          "config": {
            "label": "HeroHeadlineSpan",
            "placeholder": ""
          }
        }
      },
      "items": {
        "herobuttontext": {
          "type": "Text",
          "config": {
            "label": "HeroButtonText",
            "placeholder": ""
          }
        },
        "herobuttonlink": {
          "type": "Link",
          "config": {
            "label": "HeroButtonLink",
            "placeholder": "",
            "allowTargetBlank": false,
            "select": null
          }
        },
        "herobuttonstyle": {
          "type": "Select",
          "config": {
            "label": "HeroButtonStyle",
            "placeholder": "Choose a button style",
            "options": [
              "Solid",
              "Outline",
              "Rounded",
              "Rounded Outline",
              "Ghost"
            ],
            "default_value": "Solid"
          }
        },
        "herobuttonripple": {
          "type": "Boolean",
          "config": {
            "label": "HeroButtonRipple",
            "placeholder_false": "false",
            "placeholder_true": "true",
            "default_value": false
          }
        }
      },
      "imageUrl": "https://images.prismic.io/slice-machine/621a5ec4-0387-4bc5-9860-2dd46cbc07cd_default_ss.png?auto=compress,format"
    },
    {
      "id": "heroWithImage",
      "name": "Hero - with Image",
      "docURL": "...",
      "version": "sktwi1xtmkfgx8626",
      "description": "Hero",
      "primary": {
        "heroheadline": {
          "type": "Text",
          "config": {
            "label": "HeroHeadline",
            "placeholder": ""
          }
        },
        "heroheadlinespan": {
          "type": "Text",
          "config": {
            "label": "HeroHeadlineSpan",
            "placeholder": ""
          }
        },
        "heroimage": {
          "type": "Image",
          "config": {
            "label": "HeroImage",
            "constraint": {},
            "thumbnails": []
          }
        },
        "heroimagelocation": {
          "type": "Boolean",
          "config": {
            "label": "HeroImageLocation",
            "placeholder_false": "Left",
            "placeholder_true": "Right",
            "default_value": false
          }
        }
      },
      "items": {
        "herobuttontext": {
          "type": "Text",
          "config": {
            "label": "HeroButtonText",
            "placeholder": ""
          }
        },
        "herobuttonlink": {
          "type": "Link",
          "config": {
            "label": "HeroButtonLink",
            "placeholder": "",
            "allowTargetBlank": false,
            "select": null
          }
        },
        "herobuttonstyle": {
          "type": "Select",
          "config": {
            "label": "HeroButtonStyle",
            "placeholder": "Choose a button style",
            "options": [
              "Solid",
              "Outline",
              "Rounded",
              "Rounded Outline",
              "Ghost"
            ],
            "default_value": "Solid"
          }
        },
        "herobuttonripple": {
          "type": "Boolean",
          "config": {
            "label": "HeroButtonRipple",
            "placeholder_false": "false",
            "placeholder_true": "true",
            "default_value": false
          }
        }
      },
      "imageUrl": "https://images.prismic.io/slice-machine/621a5ec4-0387-4bc5-9860-2dd46cbc07cd_default_ss.png?auto=compress,format"
    },
    {
      "id": "heroWithBackgroundImage",
      "name": "Hero - with Background Image",
      "docURL": "...",
      "version": "sktwi1xtmkfgx8626",
      "description": "Hero",
      "primary": {
        "heroheadline": {
          "type": "Text",
          "config": {
            "label": "HeroHeadline",
            "placeholder": ""
          }
        },
        "heroheadlinespan": {
          "type": "Text",
          "config": {
            "label": "HeroHeadlineSpan",
            "placeholder": ""
          }
        },
        "herobackgroundimage": {
          "type": "Image",
          "config": {
            "label": "HeroBackgroundImage",
            "constraint": {},
            "thumbnails": []
          }
        }
      },
      "items": {
        "herobuttontext": {
          "type": "Text",
          "config": {
            "label": "HeroButtonText",
            "placeholder": ""
          }
        },
        "herobuttonlink": {
          "type": "Link",
          "config": {
            "label": "HeroButtonLink",
            "placeholder": "",
            "allowTargetBlank": false,
            "select": null
          }
        },
        "herobuttonstyle": {
          "type": "Select",
          "config": {
            "label": "HeroButtonStyle",
            "placeholder": "Choose a button style",
            "options": [
              "Solid",
              "Outline",
              "Rounded",
              "Rounded Outline",
              "Ghost"
            ],
            "default_value": "Solid"
          }
        },
        "herobuttonripple": {
          "type": "Boolean",
          "config": {
            "label": "HeroButtonRipple",
            "placeholder_false": "false",
            "placeholder_true": "true",
            "default_value": false
          }
        }
      },
      "imageUrl": "https://images.prismic.io/slice-machine/621a5ec4-0387-4bc5-9860-2dd46cbc07cd_default_ss.png?auto=compress,format"
    }
  ]
}